README.md
setup.py
sauce_finder/__init__.py
sauce_finder/sauce_finder
sauce_finder/sauce_finder.py
sauce_finder.egg-info/PKG-INFO
sauce_finder.egg-info/SOURCES.txt
sauce_finder.egg-info/dependency_links.txt
sauce_finder.egg-info/requires.txt
sauce_finder.egg-info/top_level.txt