Metadata-Version: 2.1
Name: sauce-finder
Version: 2.2.1
Summary: Script to find and download anime images
Home-page: https://gitlab.com/miicat/sauce-finder
Author: Miika Launiainen
Author-email: miika.launiainen@gmail.com
License: UNKNOWN
Platform: UNKNOWN
Classifier: Programming Language :: Python :: 3
Classifier: License :: OSI Approved :: GNU General Public License v3 (GPLv3)
Classifier: Operating System :: POSIX :: Linux
Requires-Python: >=3.0
